inventree_part_import/__init__.py
inventree_part_import/__main__.py
inventree_part_import/categories.py
inventree_part_import/cli.py
inventree_part_import/inventree_helpers.py
inventree_part_import/localization.py
inventree_part_import/part_importer.py
inventree_part_import/retries.py
inventree_part_import/config/__init__.py
inventree_part_import/config/default_categories.yaml
inventree_part_import/config/default_parameters.yaml
inventree_part_import/suppliers/__init__.py
inventree_part_import/suppliers/base.py
inventree_part_import/suppliers/supplier_digikey.py
inventree_part_import/suppliers/supplier_lcsc.py
inventree_part_import/suppliers/supplier_mouser.py
inventree_part_import/suppliers/supplier_reichelt.py
inventree_part_import/suppliers/supplier_tme.py
inventree_part_import-1.9.1.dist-info/METADATA
inventree_part_import-1.9.1.dist-info/WHEEL
inventree_part_import-1.9.1.dist-info/entry_points.txt
inventree_part_import-1.9.1.dist-info/licenses/LICENSE
inventree_part_import-1.9.1.dist-info/RECORD
