Metadata-Version: 2.4
Name: inventree-part-import
Version: 1.9.1
Summary: CLI to import parts from suppliers like DigiKey, LCSC, Mouser, etc. to InvenTree
Project-URL: Homepage, https://github.com/30350n/inventree_part_import
Author-email: Bobbe <mail@30350n.de>
License-Expression: MIT
License-File: LICENSE
Classifier: Development Status :: 5 - Production/Stable
Classifier: Environment :: Console
Classifier: Framework :: InvenTree
Classifier: License :: OSI Approved :: MIT License
Classifier: Operating System :: OS Independent
Classifier: Programming Language :: Python :: 3
Requires-Python: <4.0,>=3.10
Requires-Dist: beautifulsoup4
Requires-Dist: browser-cookie3
Requires-Dist: click
Requires-Dist: cutie
Requires-Dist: error-helper
Requires-Dist: fake-useragent
Requires-Dist: inventree<0.20.0,>=0.13.2
Requires-Dist: isocodes
Requires-Dist: mouser>=0.1.5
Requires-Dist: platformdirs>=3.2.0
Requires-Dist: pyyaml
Requires-Dist: requests
Requires-Dist: requests-oauthlib
Requires-Dist: tablib[ods,xls,xlsx]
Requires-Dist: thefuzz
Provides-Extra: dev
Requires-Dist: autopep8; extra == 'dev'
Requires-Dist: pre-commit; extra == 'dev'
Requires-Dist: pytest; extra == 'dev'
